osdata/__init__.py
osdata/module.py
osdata/test.py
osdata-0.0.3.dist-info/METADATA
osdata-0.0.3.dist-info/WHEEL
osdata-0.0.3.dist-info/top_level.txt
osdata-0.0.3.dist-info/RECORD
