Metadata-Version: 2.1
Name: osdata
Version: 0.0.3
Summary: A Universal API for discovering and managing research datasets
Author: Osyris Technologies, Inc.
Author-email: dev@osyris.io
Keywords: osyris,data,dataset,ai
